# Comparing `tmp/bigdl_friesian-2.4.0b20230626-py3-none-manylinux1_x86_64.whl.zip` & `tmp/bigdl_friesian-2.4.0b20230629-py3-none-manylinux1_x86_64.whl.zip`

## zipinfo {}

```diff
@@ -1,15 +1,15 @@
-Zip file size: 170218 bytes, number of entries: 13
--rw-------  2.0 unx      940 b- defN 23-Jun-26 06:40 bigdl/__init__.py
--rw-------  2.0 unx      927 b- defN 23-Jun-26 06:40 bigdl/friesian/__init__.py
--rw-------  2.0 unx      644 b- defN 23-Jun-26 06:40 bigdl/friesian/feature/__init__.py
--rw-------  2.0 unx   122597 b- defN 23-Jun-26 06:40 bigdl/friesian/feature/table.py
--rw-------  2.0 unx    11337 b- defN 23-Jun-26 06:40 bigdl/friesian/feature/utils.py
--rw-------  2.0 unx      621 b- defN 23-Jun-26 06:40 bigdl/friesian/models/__init__.py
--rw-------  2.0 unx     4310 b- defN 23-Jun-26 06:40 bigdl/friesian/models/tfrs_model.py
--rw-------  2.0 unx   158671 b- defN 23-Jun-26 12:01 bigdl/share/friesian/lib/bigdl-friesian-spark_2.4.6-2.4.0-SNAPSHOT-jar-with-dependencies.jar
--rw-------  2.0 unx      973 b- defN 23-Jun-26 12:01 bigdl_friesian-2.4.0b20230626.dist-info/METADATA
--rw-------  2.0 unx      106 b- defN 23-Jun-26 12:01 bigdl_friesian-2.4.0b20230626.dist-info/WHEEL
--rw-------  2.0 unx       68 b- defN 23-Jun-26 12:01 bigdl_friesian-2.4.0b20230626.dist-info/dependency_links.txt
--rw-------  2.0 unx        7 b- defN 23-Jun-26 12:01 bigdl_friesian-2.4.0b20230626.dist-info/top_level.txt
--rw-rw-r--  2.0 unx     1232 b- defN 23-Jun-26 12:01 bigdl_friesian-2.4.0b20230626.dist-info/RECORD
-13 files, 302433 bytes uncompressed, 168106 bytes compressed:  44.4%
+Zip file size: 170396 bytes, number of entries: 13
+-rw-r--r--  2.0 unx      940 b- defN 22-Oct-25 01:39 bigdl/__init__.py
+-rw-r--r--  2.0 unx      927 b- defN 22-Oct-25 01:39 bigdl/friesian/__init__.py
+-rw-r--r--  2.0 unx      644 b- defN 22-Oct-25 01:39 bigdl/friesian/feature/__init__.py
+-rw-r--r--  2.0 unx   122597 b- defN 22-Oct-26 02:04 bigdl/friesian/feature/table.py
+-rw-r--r--  2.0 unx    11337 b- defN 22-Oct-25 01:39 bigdl/friesian/feature/utils.py
+-rw-r--r--  2.0 unx      621 b- defN 22-Oct-25 01:39 bigdl/friesian/models/__init__.py
+-rw-r--r--  2.0 unx     4310 b- defN 22-Oct-25 01:39 bigdl/friesian/models/tfrs_model.py
+-rw-r--r--  2.0 unx   158705 b- defN 23-Jun-29 12:53 bigdl/share/friesian/lib/bigdl-friesian-spark_2.4.6-2.4.0-SNAPSHOT-jar-with-dependencies.jar
+-rw-r--r--  2.0 unx      973 b- defN 23-Jun-29 13:08 bigdl_friesian-2.4.0b20230629.dist-info/METADATA
+-rw-r--r--  2.0 unx      106 b- defN 23-Jun-29 13:08 bigdl_friesian-2.4.0b20230629.dist-info/WHEEL
+-rw-r--r--  2.0 unx       68 b- defN 23-Jun-29 13:08 bigdl_friesian-2.4.0b20230629.dist-info/dependency_links.txt
+-rw-r--r--  2.0 unx        7 b- defN 23-Jun-29 13:08 bigdl_friesian-2.4.0b20230629.dist-info/top_level.txt
+?rw-rw-r--  2.0 unx     1232 b- defN 23-Jun-29 13:08 bigdl_friesian-2.4.0b20230629.dist-info/RECORD
+13 files, 302467 bytes uncompressed, 168284 bytes compressed:  44.4%
```

## zipnote {}

```diff
@@ -18,23 +18,23 @@
 
 Filename: bigdl/friesian/models/tfrs_model.py
 Comment: 
 
 Filename: bigdl/share/friesian/lib/bigdl-friesian-spark_2.4.6-2.4.0-SNAPSHOT-jar-with-dependencies.jar
 Comment: 
 
-Filename: bigdl_friesian-2.4.0b20230626.dist-info/METADATA
+Filename: bigdl_friesian-2.4.0b20230629.dist-info/METADATA
 Comment: 
 
-Filename: bigdl_friesian-2.4.0b20230626.dist-info/WHEEL
+Filename: bigdl_friesian-2.4.0b20230629.dist-info/WHEEL
 Comment: 
 
-Filename: bigdl_friesian-2.4.0b20230626.dist-info/dependency_links.txt
+Filename: bigdl_friesian-2.4.0b20230629.dist-info/dependency_links.txt
 Comment: 
 
-Filename: bigdl_friesian-2.4.0b20230626.dist-info/top_level.txt
+Filename: bigdl_friesian-2.4.0b20230629.dist-info/top_level.txt
 Comment: 
 
-Filename: bigdl_friesian-2.4.0b20230626.dist-info/RECORD
+Filename: bigdl_friesian-2.4.0b20230629.dist-info/RECORD
 Comment: 
 
 Zip file comment:
```

## bigdl/share/friesian/lib/bigdl-friesian-spark_2.4.6-2.4.0-SNAPSHOT-jar-with-dependencies.jar

### zipinfo {}

```diff
@@ -1,115 +1,115 @@
-Zip file size: 158671 bytes, number of entries: 113
--rw----     2.0 fat        0 bX defN 23-Jun-26 04:54 META-INF/
--rw----     2.0 fat      130 bl defN 23-Jun-26 04:54 META-INF/MANIFEST.MF
--rw----     2.0 fat        0 bl defN 23-Jun-26 04:54 com/
--rw----     2.0 fat        0 bl defN 23-Jun-26 04:54 com/intel/
--rw----     2.0 fat        0 bl defN 23-Jun-26 04:54 com/intel/analytics/
--rw----     2.0 fat        0 bl defN 23-Jun-26 04:54 com/intel/analytics/bigdl/
--rw----     2.0 fat        0 bl defN 23-Jun-26 04:54 com/intel/analytics/bigdl/friesian/
--rw----     2.0 fat        0 bl defN 23-Jun-26 04:54 com/intel/analytics/bigdl/friesian/feature/
--rw----     2.0 fat     3076 bl defN 23-Jun-26 04:54 com/intel/analytics/bigdl/friesian/feature/Utils$$anonfun$maskArr$1.class
--rw----     2.0 fat     3238 bl defN 23-Jun-26 04:54 com/intel/analytics/bigdl/friesian/feature/Utils$$typecreator3$1.class
--rw----     2.0 fat     1465 bl defN 23-Jun-26 04:54 com/intel/analytics/bigdl/friesian/feature/Utils$$anonfun$getMedian$1.class
--rw----     2.0 fat     1365 bl defN 23-Jun-26 04:54 com/intel/analytics/bigdl/friesian/feature/Utils$$anonfun$10.class
--rw----     2.0 fat     1779 bl defN 23-Jun-26 04:54 com/intel/analytics/bigdl/friesian/feature/Utils$$anonfun$12$$anonfun$apply$3.class
--rw----     2.0 fat     1343 bl defN 23-Jun-26 04:54 com/intel/analytics/bigdl/friesian/feature/Utils$$anonfun$maskArr$1$$anonfun$1.class
--rw----     2.0 fat     2604 bl defN 23-Jun-26 04:54 com/intel/analytics/bigdl/friesian/feature/Utils$$anonfun$addNegativeList$1.class
--rw----     2.0 fat     2572 bl defN 23-Jun-26 04:54 com/intel/analytics/bigdl/friesian/feature/Utils$$anonfun$padMatrix$1$$anonfun$8.class
--rw----     2.0 fat     2308 bl defN 23-Jun-26 04:54 com/intel/analytics/bigdl/friesian/feature/Utils$$anonfun$13$$anonfun$apply$9.class
--rw----     2.0 fat     1949 bl defN 23-Jun-26 04:54 com/intel/analytics/bigdl/friesian/feature/Utils$$anonfun$6$$anonfun$apply$6.class
--rw----     2.0 fat     1818 bl defN 23-Jun-26 04:54 com/intel/analytics/bigdl/friesian/feature/Utils$$anonfun$4.class
--rw----     2.0 fat     3097 bl defN 23-Jun-26 04:54 com/intel/analytics/bigdl/friesian/feature/Utils$$anonfun$6.class
--rw----     2.0 fat     1471 bl defN 23-Jun-26 04:54 com/intel/analytics/bigdl/friesian/feature/Utils$$anonfun$getClipFunc$3.class
--rw----     2.0 fat     3087 bl defN 23-Jun-26 04:54 com/intel/analytics/bigdl/friesian/feature/Utils$$anonfun$addNegtiveItem$1.class
--rw----     2.0 fat     1343 bl defN 23-Jun-26 04:54 com/intel/analytics/bigdl/friesian/feature/Utils$$anonfun$maskArr$1$$anonfun$3.class
--rw----     2.0 fat     2489 bl defN 23-Jun-26 04:54 com/intel/analytics/bigdl/friesian/feature/Utils$$anonfun$12.class
--rw----     2.0 fat     1204 bl defN 23-Jun-26 04:54 com/intel/analytics/bigdl/friesian/feature/Utils$$anonfun$4$$anonfun$apply$mcII$sp$1.class
--rw----     2.0 fat     3196 bl defN 23-Jun-26 04:54 com/intel/analytics/bigdl/friesian/feature/Utils$$anonfun$padArr$1.class
--rw----     2.0 fat     1379 bl defN 23-Jun-26 04:54 com/intel/analytics/bigdl/friesian/feature/Utils$$anonfun$getClipFunc$2.class
--rw----     2.0 fat     3651 bl defN 23-Jun-26 04:54 com/intel/analytics/bigdl/friesian/feature/Utils$$anonfun$padMatrix$1.class
--rw----     2.0 fat     1555 bl defN 23-Jun-26 04:54 com/intel/analytics/bigdl/friesian/feature/Utils$$anonfun$padMatrix$1$$anonfun$8$$anonfun$apply$7.class
--rw----     2.0 fat     2141 bl defN 23-Jun-26 04:54 com/intel/analytics/bigdl/friesian/feature/Utils$$anonfun$addNegativeList$1$$anonfun$9$$anonfun$apply$2.class
--rw----     2.0 fat    19719 bl defN 23-Jun-26 04:54 com/intel/analytics/bigdl/friesian/feature/Utils$.class
--rw----     2.0 fat     1343 bl defN 23-Jun-26 04:54 com/intel/analytics/bigdl/friesian/feature/Utils$$anonfun$maskArr$1$$anonfun$2.class
--rw----     2.0 fat     1974 bl defN 23-Jun-26 04:54 com/intel/analytics/bigdl/friesian/feature/Utils$$anonfun$13$$anonfun$apply$9$$anonfun$apply$4.class
--rw----     2.0 fat     2666 bl defN 23-Jun-26 04:54 com/intel/analytics/bigdl/friesian/feature/Utils$$anonfun$13.class
--rw----     2.0 fat     2892 bl defN 23-Jun-26 04:54 com/intel/analytics/bigdl/friesian/feature/Utils$$anonfun$addNegativeList$1$$anonfun$9.class
--rw----     2.0 fat     1368 bl defN 23-Jun-26 04:54 com/intel/analytics/bigdl/friesian/feature/Utils$$anonfun$12$$anonfun$apply$3$$anonfun$apply$mcII$sp$2.class
--rw----     2.0 fat     3166 bl defN 23-Jun-26 04:54 com/intel/analytics/bigdl/friesian/feature/Utils$$typecreator1$1.class
--rw----     2.0 fat     1478 bl defN 23-Jun-26 04:54 com/intel/analytics/bigdl/friesian/feature/Utils$$anonfun$6$$anonfun$apply$5.class
--rw----     2.0 fat     2235 bl defN 23-Jun-26 04:54 com/intel/analytics/bigdl/friesian/feature/Utils$$anonfun$getIndex$1.class
--rw----     2.0 fat     3238 bl defN 23-Jun-26 04:54 com/intel/analytics/bigdl/friesian/feature/Utils$$typecreator4$1.class
--rw----     2.0 fat     2984 bl defN 23-Jun-26 04:54 com/intel/analytics/bigdl/friesian/feature/Utils$$anonfun$5.class
--rw----     2.0 fat     1671 bl defN 23-Jun-26 04:54 com/intel/analytics/bigdl/friesian/feature/Utils$$anonfun$addNegtiveItem$1$$anonfun$apply$1.class
--rw----     2.0 fat     1379 bl defN 23-Jun-26 04:54 com/intel/analytics/bigdl/friesian/feature/Utils$$anonfun$getClipFunc$1.class
--rw----     2.0 fat     1544 bl defN 23-Jun-26 04:54 com/intel/analytics/bigdl/friesian/feature/Utils$$anonfun$13$$anonfun$apply$9$$anonfun$apply$4$$anonfun$apply$mcII$sp$3.class
--rw----     2.0 fat     1503 bl defN 23-Jun-26 04:54 com/intel/analytics/bigdl/friesian/feature/Utils$$anonfun$addNegtiveItem$1$$anonfun$apply$8.class
--rw----     2.0 fat     1610 bl defN 23-Jun-26 04:54 com/intel/analytics/bigdl/friesian/feature/Utils$$anonfun$11.class
--rw----     2.0 fat     7431 bl defN 23-Jun-26 04:54 com/intel/analytics/bigdl/friesian/feature/Utils.class
--rw----     2.0 fat     1374 bl defN 23-Jun-26 04:54 com/intel/analytics/bigdl/friesian/feature/Utils$$anonfun$padArr$1$$anonfun$7.class
--rw----     2.0 fat     3166 bl defN 23-Jun-26 04:54 com/intel/analytics/bigdl/friesian/feature/Utils$$typecreator2$1.class
--rw----     2.0 fat        0 bl defN 23-Jun-26 04:54 com/intel/analytics/bigdl/friesian/python/
--rw----     2.0 fat     1621 bl defN 23-Jun-26 04:54 com/intel/analytics/bigdl/friesian/python/PythonFriesian$$anonfun$21$$anonfun$apply$2.class
--rw----     2.0 fat     2186 bl defN 23-Jun-26 04:54 com/intel/analytics/bigdl/friesian/python/PythonFriesian$$anonfun$23.class
--rw----     2.0 fat     3054 bl defN 23-Jun-26 04:54 com/intel/analytics/bigdl/friesian/python/PythonFriesian$$anonfun$9$$anonfun$12.class
--rw----     2.0 fat     4885 bl defN 23-Jun-26 04:54 com/intel/analytics/bigdl/friesian/python/PythonFriesian$$anonfun$clip$1.class
--rw----     2.0 fat     4182 bl defN 23-Jun-26 04:54 com/intel/analytics/bigdl/friesian/python/PythonFriesian$$anonfun$crossColumns$1.class
--rw----     2.0 fat     2353 bl defN 23-Jun-26 04:54 com/intel/analytics/bigdl/friesian/python/PythonFriesian$$anonfun$addValueFeatures$1.class
--rw----     2.0 fat     2868 bl defN 23-Jun-26 04:54 com/intel/analytics/bigdl/friesian/python/PythonFriesian$$anonfun$mask$1.class
--rw----     2.0 fat     3433 bl defN 23-Jun-26 04:54 com/intel/analytics/bigdl/friesian/python/PythonFriesian$$anonfun$postPad$1$$typecreator13$1.class
--rw----     2.0 fat     1775 bl defN 23-Jun-26 04:54 com/intel/analytics/bigdl/friesian/python/PythonFriesian$$anonfun$18.class
--rw----     2.0 fat     3772 bl defN 23-Jun-26 04:54 com/intel/analytics/bigdl/friesian/python/PythonFriesian$$anonfun$postPad$1$$typecreator19$1.class
--rw----     2.0 fat     3700 bl defN 23-Jun-26 04:54 com/intel/analytics/bigdl/friesian/python/PythonFriesian$$anonfun$postPad$1$$typecreator11$1.class
--rw----     2.0 fat     3436 bl defN 23-Jun-26 04:54 com/intel/analytics/bigdl/friesian/python/PythonFriesian$$anonfun$postPad$1$$typecreator17$1.class
--rw----     2.0 fat     3362 bl defN 23-Jun-26 04:54 com/intel/analytics/bigdl/friesian/python/PythonFriesian$$anonfun$postPad$1$$typecreator9$1.class
--rw----     2.0 fat     3985 bl defN 23-Jun-26 04:54 com/intel/analytics/bigdl/friesian/python/PythonFriesian$$anonfun$20.class
--rw----     2.0 fat     3350 bl defN 23-Jun-26 04:54 com/intel/analytics/bigdl/friesian/python/PythonFriesian$$anonfun$postPad$1$$typecreator4$1.class
--rw----     2.0 fat     3165 bl defN 23-Jun-26 04:54 com/intel/analytics/bigdl/friesian/python/PythonFriesian$$anonfun$log$1.class
--rw----     2.0 fat     3353 bl defN 23-Jun-26 04:54 com/intel/analytics/bigdl/friesian/python/PythonFriesian$$anonfun$postPad$1$$typecreator8$1.class
--rw----     2.0 fat     3861 bl defN 23-Jun-26 04:54 com/intel/analytics/bigdl/friesian/python/PythonFriesian$$anonfun$postPad$1$$typecreator16$1.class
--rw----     2.0 fat     1969 bl defN 23-Jun-26 04:54 com/intel/analytics/bigdl/friesian/python/PythonFriesian$$anonfun$6.class
--rw----     2.0 fat     1697 bl defN 23-Jun-26 04:54 com/intel/analytics/bigdl/friesian/python/PythonFriesian$$anonfun$9$$anonfun$10.class
--rw----     2.0 fat     1937 bl defN 23-Jun-26 04:54 com/intel/analytics/bigdl/friesian/python/PythonFriesian$.class
--rw----     2.0 fat    33887 bl defN 23-Jun-26 04:54 com/intel/analytics/bigdl/friesian/python/PythonFriesian.class
--rw----     2.0 fat     3859 bl defN 23-Jun-26 04:54 com/intel/analytics/bigdl/friesian/python/PythonFriesian$$anonfun$postPad$1$$typecreator14$1.class
--rw----     2.0 fat     4033 bl defN 23-Jun-26 04:54 com/intel/analytics/bigdl/friesian/python/PythonFriesian$$anonfun$9.class
--rw----     2.0 fat     1806 bl defN 23-Jun-26 04:54 com/intel/analytics/bigdl/friesian/python/PythonFriesian$$anonfun$22.class
--rw----     2.0 fat     3360 bl defN 23-Jun-26 04:54 com/intel/analytics/bigdl/friesian/python/PythonFriesian$$anonfun$postPad$1$$typecreator7$1.class
--rw----     2.0 fat     1509 bl defN 23-Jun-26 04:54 com/intel/analytics/bigdl/friesian/python/PythonFriesian$$anonfun$1.class
--rw----     2.0 fat     1625 bl defN 23-Jun-26 04:54 com/intel/analytics/bigdl/friesian/python/PythonFriesian$$anonfun$crossColumns$1$$anonfun$apply$mcVI$sp$1.class
--rw----     2.0 fat     3377 bl defN 23-Jun-26 04:54 com/intel/analytics/bigdl/friesian/python/PythonFriesian$$typecreator1$1.class
--rw----     2.0 fat     3838 bl defN 23-Jun-26 04:54 com/intel/analytics/bigdl/friesian/python/PythonFriesian$$anonfun$postPad$1$$typecreator18$1.class
--rw----     2.0 fat     3702 bl defN 23-Jun-26 04:54 com/intel/analytics/bigdl/friesian/python/PythonFriesian$$typecreator2$1.class
--rw----     2.0 fat     4295 bl defN 23-Jun-26 04:54 com/intel/analytics/bigdl/friesian/python/PythonFriesian$$anonfun$9$$anonfun$12$$anonfun$13.class
--rw----     2.0 fat     1573 bl defN 23-Jun-26 04:54 com/intel/analytics/bigdl/friesian/python/PythonFriesian$$anonfun$17.class
--rw----     2.0 fat     9139 bl defN 23-Jun-26 04:54 com/intel/analytics/bigdl/friesian/python/PythonFriesian$$anonfun$postPad$1.class
--rw----     2.0 fat     1708 bl defN 23-Jun-26 04:54 com/intel/analytics/bigdl/friesian/python/PythonFriesian$$anonfun$9$$anonfun$11.class
--rw----     2.0 fat     3045 bl defN 23-Jun-26 04:54 com/intel/analytics/bigdl/friesian/python/PythonFriesian$$anonfun$log$2.class
--rw----     2.0 fat     2885 bl defN 23-Jun-26 04:54 com/intel/analytics/bigdl/friesian/python/PythonFriesian$$anonfun$clip$2.class
--rw----     2.0 fat     1768 bl defN 23-Jun-26 04:54 com/intel/analytics/bigdl/friesian/python/PythonFriesian$$anonfun$14.class
--rw----     2.0 fat     3434 bl defN 23-Jun-26 04:54 com/intel/analytics/bigdl/friesian/python/PythonFriesian$$anonfun$postPad$1$$typecreator15$1.class
--rw----     2.0 fat     2517 bl defN 23-Jun-26 04:54 com/intel/analytics/bigdl/friesian/python/PythonFriesian$$anonfun$5.class
--rw----     2.0 fat     1809 bl defN 23-Jun-26 04:54 com/intel/analytics/bigdl/friesian/python/PythonFriesian$$anonfun$19.class
--rw----     2.0 fat     3395 bl defN 23-Jun-26 04:54 com/intel/analytics/bigdl/friesian/python/PythonFriesian$$anonfun$4.class
--rw----     2.0 fat     1724 bl defN 23-Jun-26 04:54 com/intel/analytics/bigdl/friesian/python/PythonFriesian$$anonfun$15.class
--rw----     2.0 fat     3691 bl defN 23-Jun-26 04:54 com/intel/analytics/bigdl/friesian/python/PythonFriesian$$anonfun$postPad$1$$typecreator10$1.class
--rw----     2.0 fat     3227 bl defN 23-Jun-26 04:54 com/intel/analytics/bigdl/friesian/python/PythonFriesian$$anonfun$8.class
--rw----     2.0 fat     3331 bl defN 23-Jun-26 04:54 com/intel/analytics/bigdl/friesian/python/PythonFriesian$$typecreator3$1.class
--rw----     2.0 fat     3359 bl defN 23-Jun-26 04:54 com/intel/analytics/bigdl/friesian/python/PythonFriesian$$anonfun$postPad$1$$typecreator5$1.class
--rw----     2.0 fat     1641 bl defN 23-Jun-26 04:54 com/intel/analytics/bigdl/friesian/python/PythonFriesian$$anonfun$3.class
--rw----     2.0 fat     2026 bl defN 23-Jun-26 04:54 com/intel/analytics/bigdl/friesian/python/PythonFriesian$$anonfun$2.class
--rw----     2.0 fat     2202 bl defN 23-Jun-26 04:54 com/intel/analytics/bigdl/friesian/python/PythonFriesian$$anonfun$com$intel$analytics$bigdl$friesian$python$PythonFriesian$$crossColumns$1$1.class
--rw----     2.0 fat     2917 bl defN 23-Jun-26 04:54 com/intel/analytics/bigdl/friesian/python/PythonFriesian$$anonfun$21.class
--rw----     2.0 fat     1898 bl defN 23-Jun-26 04:54 com/intel/analytics/bigdl/friesian/python/PythonFriesian$$anonfun$5$$anonfun$apply$1.class
--rw----     2.0 fat     1706 bl defN 23-Jun-26 04:54 com/intel/analytics/bigdl/friesian/python/PythonFriesian$$anonfun$16.class
--rw----     2.0 fat     3351 bl defN 23-Jun-26 04:54 com/intel/analytics/bigdl/friesian/python/PythonFriesian$$anonfun$postPad$1$$typecreator6$1.class
--rw----     2.0 fat     2092 bl defN 23-Jun-26 04:54 com/intel/analytics/bigdl/friesian/python/PythonFriesian$$anonfun$21$$anonfun$apply$3.class
--rw----     2.0 fat     1892 bl defN 23-Jun-26 04:54 com/intel/analytics/bigdl/friesian/python/PythonFriesian$$anonfun$7.class
--rw----     2.0 fat     3858 bl defN 23-Jun-26 04:54 com/intel/analytics/bigdl/friesian/python/PythonFriesian$$anonfun$postPad$1$$typecreator12$1.class
--rw----     2.0 fat     3058 bl defN 23-Jun-26 04:54 app.properties
--rw----     2.0 fat        0 bl defN 23-Jun-26 04:54 META-INF/maven/
--rw----     2.0 fat        0 bl defN 23-Jun-26 04:54 META-INF/maven/com.intel.analytics.bigdl/
--rw----     2.0 fat        0 bl defN 23-Jun-26 04:54 META-INF/maven/com.intel.analytics.bigdl/bigdl-friesian-spark_2.4.6/
--rw----     2.0 fat    28637 bl defN 23-Jun-25 23:40 META-INF/maven/com.intel.analytics.bigdl/bigdl-friesian-spark_2.4.6/pom.xml
--rw----     2.0 fat      145 bl defN 23-Jun-26 04:51 META-INF/maven/com.intel.analytics.bigdl/bigdl-friesian-spark_2.4.6/pom.properties
-113 files, 342264 bytes uncompressed, 130987 bytes compressed:  61.7%
+Zip file size: 158705 bytes, number of entries: 113
+-rw----     2.0 fat        0 bX defN 23-Jun-29 12:46 META-INF/
+-rw----     2.0 fat      130 bl defN 23-Jun-29 12:46 META-INF/MANIFEST.MF
+-rw----     2.0 fat     3032 bl defN 23-Jun-29 12:46 app.properties
+-rw----     2.0 fat        0 bl defN 23-Jun-29 12:46 com/
+-rw----     2.0 fat        0 bl defN 23-Jun-29 12:46 com/intel/
+-rw----     2.0 fat        0 bl defN 23-Jun-29 12:46 com/intel/analytics/
+-rw----     2.0 fat        0 bl defN 23-Jun-29 12:46 com/intel/analytics/bigdl/
+-rw----     2.0 fat        0 bl defN 23-Jun-29 12:46 com/intel/analytics/bigdl/friesian/
+-rw----     2.0 fat        0 bl defN 23-Jun-29 12:46 com/intel/analytics/bigdl/friesian/python/
+-rw----     2.0 fat     2885 bl defN 23-Jun-29 12:46 com/intel/analytics/bigdl/friesian/python/PythonFriesian$$anonfun$clip$2.class
+-rw----     2.0 fat     3434 bl defN 23-Jun-29 12:46 com/intel/analytics/bigdl/friesian/python/PythonFriesian$$anonfun$postPad$1$$typecreator15$1.class
+-rw----     2.0 fat     3360 bl defN 23-Jun-29 12:46 com/intel/analytics/bigdl/friesian/python/PythonFriesian$$anonfun$postPad$1$$typecreator7$1.class
+-rw----     2.0 fat     3045 bl defN 23-Jun-29 12:46 com/intel/analytics/bigdl/friesian/python/PythonFriesian$$anonfun$log$2.class
+-rw----     2.0 fat     3165 bl defN 23-Jun-29 12:46 com/intel/analytics/bigdl/friesian/python/PythonFriesian$$anonfun$log$1.class
+-rw----     2.0 fat     4182 bl defN 23-Jun-29 12:46 com/intel/analytics/bigdl/friesian/python/PythonFriesian$$anonfun$crossColumns$1.class
+-rw----     2.0 fat     1573 bl defN 23-Jun-29 12:46 com/intel/analytics/bigdl/friesian/python/PythonFriesian$$anonfun$17.class
+-rw----     2.0 fat    33887 bl defN 23-Jun-29 12:46 com/intel/analytics/bigdl/friesian/python/PythonFriesian.class
+-rw----     2.0 fat     9139 bl defN 23-Jun-29 12:46 com/intel/analytics/bigdl/friesian/python/PythonFriesian$$anonfun$postPad$1.class
+-rw----     2.0 fat     3351 bl defN 23-Jun-29 12:46 com/intel/analytics/bigdl/friesian/python/PythonFriesian$$anonfun$postPad$1$$typecreator6$1.class
+-rw----     2.0 fat     4885 bl defN 23-Jun-29 12:46 com/intel/analytics/bigdl/friesian/python/PythonFriesian$$anonfun$clip$1.class
+-rw----     2.0 fat     3395 bl defN 23-Jun-29 12:46 com/intel/analytics/bigdl/friesian/python/PythonFriesian$$anonfun$4.class
+-rw----     2.0 fat     2868 bl defN 23-Jun-29 12:46 com/intel/analytics/bigdl/friesian/python/PythonFriesian$$anonfun$mask$1.class
+-rw----     2.0 fat     1806 bl defN 23-Jun-29 12:46 com/intel/analytics/bigdl/friesian/python/PythonFriesian$$anonfun$22.class
+-rw----     2.0 fat     3691 bl defN 23-Jun-29 12:46 com/intel/analytics/bigdl/friesian/python/PythonFriesian$$anonfun$postPad$1$$typecreator10$1.class
+-rw----     2.0 fat     2186 bl defN 23-Jun-29 12:46 com/intel/analytics/bigdl/friesian/python/PythonFriesian$$anonfun$23.class
+-rw----     2.0 fat     1809 bl defN 23-Jun-29 12:46 com/intel/analytics/bigdl/friesian/python/PythonFriesian$$anonfun$19.class
+-rw----     2.0 fat     3377 bl defN 23-Jun-29 12:46 com/intel/analytics/bigdl/friesian/python/PythonFriesian$$typecreator1$1.class
+-rw----     2.0 fat     3350 bl defN 23-Jun-29 12:46 com/intel/analytics/bigdl/friesian/python/PythonFriesian$$anonfun$postPad$1$$typecreator4$1.class
+-rw----     2.0 fat     1621 bl defN 23-Jun-29 12:46 com/intel/analytics/bigdl/friesian/python/PythonFriesian$$anonfun$21$$anonfun$apply$2.class
+-rw----     2.0 fat     3362 bl defN 23-Jun-29 12:46 com/intel/analytics/bigdl/friesian/python/PythonFriesian$$anonfun$postPad$1$$typecreator9$1.class
+-rw----     2.0 fat     3359 bl defN 23-Jun-29 12:46 com/intel/analytics/bigdl/friesian/python/PythonFriesian$$anonfun$postPad$1$$typecreator5$1.class
+-rw----     2.0 fat     3702 bl defN 23-Jun-29 12:46 com/intel/analytics/bigdl/friesian/python/PythonFriesian$$typecreator2$1.class
+-rw----     2.0 fat     3772 bl defN 23-Jun-29 12:46 com/intel/analytics/bigdl/friesian/python/PythonFriesian$$anonfun$postPad$1$$typecreator19$1.class
+-rw----     2.0 fat     4295 bl defN 23-Jun-29 12:46 com/intel/analytics/bigdl/friesian/python/PythonFriesian$$anonfun$9$$anonfun$12$$anonfun$13.class
+-rw----     2.0 fat     3436 bl defN 23-Jun-29 12:46 com/intel/analytics/bigdl/friesian/python/PythonFriesian$$anonfun$postPad$1$$typecreator17$1.class
+-rw----     2.0 fat     1724 bl defN 23-Jun-29 12:46 com/intel/analytics/bigdl/friesian/python/PythonFriesian$$anonfun$15.class
+-rw----     2.0 fat     1969 bl defN 23-Jun-29 12:46 com/intel/analytics/bigdl/friesian/python/PythonFriesian$$anonfun$6.class
+-rw----     2.0 fat     1509 bl defN 23-Jun-29 12:46 com/intel/analytics/bigdl/friesian/python/PythonFriesian$$anonfun$1.class
+-rw----     2.0 fat     3700 bl defN 23-Jun-29 12:46 com/intel/analytics/bigdl/friesian/python/PythonFriesian$$anonfun$postPad$1$$typecreator11$1.class
+-rw----     2.0 fat     3227 bl defN 23-Jun-29 12:46 com/intel/analytics/bigdl/friesian/python/PythonFriesian$$anonfun$8.class
+-rw----     2.0 fat     3858 bl defN 23-Jun-29 12:46 com/intel/analytics/bigdl/friesian/python/PythonFriesian$$anonfun$postPad$1$$typecreator12$1.class
+-rw----     2.0 fat     3861 bl defN 23-Jun-29 12:46 com/intel/analytics/bigdl/friesian/python/PythonFriesian$$anonfun$postPad$1$$typecreator16$1.class
+-rw----     2.0 fat     1706 bl defN 23-Jun-29 12:46 com/intel/analytics/bigdl/friesian/python/PythonFriesian$$anonfun$16.class
+-rw----     2.0 fat     2517 bl defN 23-Jun-29 12:46 com/intel/analytics/bigdl/friesian/python/PythonFriesian$$anonfun$5.class
+-rw----     2.0 fat     3331 bl defN 23-Jun-29 12:46 com/intel/analytics/bigdl/friesian/python/PythonFriesian$$typecreator3$1.class
+-rw----     2.0 fat     2353 bl defN 23-Jun-29 12:46 com/intel/analytics/bigdl/friesian/python/PythonFriesian$$anonfun$addValueFeatures$1.class
+-rw----     2.0 fat     1898 bl defN 23-Jun-29 12:46 com/intel/analytics/bigdl/friesian/python/PythonFriesian$$anonfun$5$$anonfun$apply$1.class
+-rw----     2.0 fat     3859 bl defN 23-Jun-29 12:46 com/intel/analytics/bigdl/friesian/python/PythonFriesian$$anonfun$postPad$1$$typecreator14$1.class
+-rw----     2.0 fat     2202 bl defN 23-Jun-29 12:46 com/intel/analytics/bigdl/friesian/python/PythonFriesian$$anonfun$com$intel$analytics$bigdl$friesian$python$PythonFriesian$$crossColumns$1$1.class
+-rw----     2.0 fat     1937 bl defN 23-Jun-29 12:46 com/intel/analytics/bigdl/friesian/python/PythonFriesian$.class
+-rw----     2.0 fat     1625 bl defN 23-Jun-29 12:46 com/intel/analytics/bigdl/friesian/python/PythonFriesian$$anonfun$crossColumns$1$$anonfun$apply$mcVI$sp$1.class
+-rw----     2.0 fat     1708 bl defN 23-Jun-29 12:46 com/intel/analytics/bigdl/friesian/python/PythonFriesian$$anonfun$9$$anonfun$11.class
+-rw----     2.0 fat     4033 bl defN 23-Jun-29 12:46 com/intel/analytics/bigdl/friesian/python/PythonFriesian$$anonfun$9.class
+-rw----     2.0 fat     1892 bl defN 23-Jun-29 12:46 com/intel/analytics/bigdl/friesian/python/PythonFriesian$$anonfun$7.class
+-rw----     2.0 fat     3433 bl defN 23-Jun-29 12:46 com/intel/analytics/bigdl/friesian/python/PythonFriesian$$anonfun$postPad$1$$typecreator13$1.class
+-rw----     2.0 fat     2917 bl defN 23-Jun-29 12:46 com/intel/analytics/bigdl/friesian/python/PythonFriesian$$anonfun$21.class
+-rw----     2.0 fat     1697 bl defN 23-Jun-29 12:46 com/intel/analytics/bigdl/friesian/python/PythonFriesian$$anonfun$9$$anonfun$10.class
+-rw----     2.0 fat     3985 bl defN 23-Jun-29 12:46 com/intel/analytics/bigdl/friesian/python/PythonFriesian$$anonfun$20.class
+-rw----     2.0 fat     3838 bl defN 23-Jun-29 12:46 com/intel/analytics/bigdl/friesian/python/PythonFriesian$$anonfun$postPad$1$$typecreator18$1.class
+-rw----     2.0 fat     1641 bl defN 23-Jun-29 12:46 com/intel/analytics/bigdl/friesian/python/PythonFriesian$$anonfun$3.class
+-rw----     2.0 fat     3353 bl defN 23-Jun-29 12:46 com/intel/analytics/bigdl/friesian/python/PythonFriesian$$anonfun$postPad$1$$typecreator8$1.class
+-rw----     2.0 fat     2092 bl defN 23-Jun-29 12:46 com/intel/analytics/bigdl/friesian/python/PythonFriesian$$anonfun$21$$anonfun$apply$3.class
+-rw----     2.0 fat     1775 bl defN 23-Jun-29 12:46 com/intel/analytics/bigdl/friesian/python/PythonFriesian$$anonfun$18.class
+-rw----     2.0 fat     1768 bl defN 23-Jun-29 12:46 com/intel/analytics/bigdl/friesian/python/PythonFriesian$$anonfun$14.class
+-rw----     2.0 fat     3054 bl defN 23-Jun-29 12:46 com/intel/analytics/bigdl/friesian/python/PythonFriesian$$anonfun$9$$anonfun$12.class
+-rw----     2.0 fat     2026 bl defN 23-Jun-29 12:46 com/intel/analytics/bigdl/friesian/python/PythonFriesian$$anonfun$2.class
+-rw----     2.0 fat        0 bl defN 23-Jun-29 12:46 com/intel/analytics/bigdl/friesian/feature/
+-rw----     2.0 fat     1779 bl defN 23-Jun-29 12:46 com/intel/analytics/bigdl/friesian/feature/Utils$$anonfun$12$$anonfun$apply$3.class
+-rw----     2.0 fat     2984 bl defN 23-Jun-29 12:46 com/intel/analytics/bigdl/friesian/feature/Utils$$anonfun$5.class
+-rw----     2.0 fat     3651 bl defN 23-Jun-29 12:46 com/intel/analytics/bigdl/friesian/feature/Utils$$anonfun$padMatrix$1.class
+-rw----     2.0 fat     2308 bl defN 23-Jun-29 12:46 com/intel/analytics/bigdl/friesian/feature/Utils$$anonfun$13$$anonfun$apply$9.class
+-rw----     2.0 fat     3097 bl defN 23-Jun-29 12:46 com/intel/analytics/bigdl/friesian/feature/Utils$$anonfun$6.class
+-rw----     2.0 fat     2910 bl defN 23-Jun-29 12:46 com/intel/analytics/bigdl/friesian/feature/Utils$$anonfun$addNegativeList$1$$anonfun$9.class
+-rw----     2.0 fat     3105 bl defN 23-Jun-29 12:46 com/intel/analytics/bigdl/friesian/feature/Utils$$anonfun$addNegtiveItem$1.class
+-rw----     2.0 fat     1471 bl defN 23-Jun-29 12:46 com/intel/analytics/bigdl/friesian/feature/Utils$$anonfun$getClipFunc$3.class
+-rw----     2.0 fat     7431 bl defN 23-Jun-29 12:46 com/intel/analytics/bigdl/friesian/feature/Utils.class
+-rw----     2.0 fat     1379 bl defN 23-Jun-29 12:46 com/intel/analytics/bigdl/friesian/feature/Utils$$anonfun$getClipFunc$2.class
+-rw----     2.0 fat     3238 bl defN 23-Jun-29 12:46 com/intel/analytics/bigdl/friesian/feature/Utils$$typecreator3$1.class
+-rw----     2.0 fat     1204 bl defN 23-Jun-29 12:46 com/intel/analytics/bigdl/friesian/feature/Utils$$anonfun$4$$anonfun$apply$mcII$sp$1.class
+-rw----     2.0 fat     1949 bl defN 23-Jun-29 12:46 com/intel/analytics/bigdl/friesian/feature/Utils$$anonfun$6$$anonfun$apply$6.class
+-rw----     2.0 fat     1689 bl defN 23-Jun-29 12:46 com/intel/analytics/bigdl/friesian/feature/Utils$$anonfun$addNegtiveItem$1$$anonfun$apply$1.class
+-rw----     2.0 fat     1343 bl defN 23-Jun-29 12:46 com/intel/analytics/bigdl/friesian/feature/Utils$$anonfun$maskArr$1$$anonfun$2.class
+-rw----     2.0 fat     2235 bl defN 23-Jun-29 12:46 com/intel/analytics/bigdl/friesian/feature/Utils$$anonfun$getIndex$1.class
+-rw----     2.0 fat     1465 bl defN 23-Jun-29 12:46 com/intel/analytics/bigdl/friesian/feature/Utils$$anonfun$getMedian$1.class
+-rw----     2.0 fat     1368 bl defN 23-Jun-29 12:46 com/intel/analytics/bigdl/friesian/feature/Utils$$anonfun$12$$anonfun$apply$3$$anonfun$apply$mcII$sp$2.class
+-rw----     2.0 fat     3076 bl defN 23-Jun-29 12:46 com/intel/analytics/bigdl/friesian/feature/Utils$$anonfun$maskArr$1.class
+-rw----     2.0 fat     2666 bl defN 23-Jun-29 12:46 com/intel/analytics/bigdl/friesian/feature/Utils$$anonfun$13.class
+-rw----     2.0 fat     1343 bl defN 23-Jun-29 12:46 com/intel/analytics/bigdl/friesian/feature/Utils$$anonfun$maskArr$1$$anonfun$3.class
+-rw----     2.0 fat     1343 bl defN 23-Jun-29 12:46 com/intel/analytics/bigdl/friesian/feature/Utils$$anonfun$maskArr$1$$anonfun$1.class
+-rw----     2.0 fat     1818 bl defN 23-Jun-29 12:46 com/intel/analytics/bigdl/friesian/feature/Utils$$anonfun$4.class
+-rw----     2.0 fat     2489 bl defN 23-Jun-29 12:46 com/intel/analytics/bigdl/friesian/feature/Utils$$anonfun$12.class
+-rw----     2.0 fat     1555 bl defN 23-Jun-29 12:46 com/intel/analytics/bigdl/friesian/feature/Utils$$anonfun$padMatrix$1$$anonfun$8$$anonfun$apply$7.class
+-rw----     2.0 fat     1544 bl defN 23-Jun-29 12:46 com/intel/analytics/bigdl/friesian/feature/Utils$$anonfun$13$$anonfun$apply$9$$anonfun$apply$4$$anonfun$apply$mcII$sp$3.class
+-rw----     2.0 fat     3166 bl defN 23-Jun-29 12:46 com/intel/analytics/bigdl/friesian/feature/Utils$$typecreator1$1.class
+-rw----     2.0 fat     2572 bl defN 23-Jun-29 12:46 com/intel/analytics/bigdl/friesian/feature/Utils$$anonfun$padMatrix$1$$anonfun$8.class
+-rw----     2.0 fat    19746 bl defN 23-Jun-29 12:46 com/intel/analytics/bigdl/friesian/feature/Utils$.class
+-rw----     2.0 fat     1974 bl defN 23-Jun-29 12:46 com/intel/analytics/bigdl/friesian/feature/Utils$$anonfun$13$$anonfun$apply$9$$anonfun$apply$4.class
+-rw----     2.0 fat     1503 bl defN 23-Jun-29 12:46 com/intel/analytics/bigdl/friesian/feature/Utils$$anonfun$addNegtiveItem$1$$anonfun$apply$8.class
+-rw----     2.0 fat     3196 bl defN 23-Jun-29 12:46 com/intel/analytics/bigdl/friesian/feature/Utils$$anonfun$padArr$1.class
+-rw----     2.0 fat     1610 bl defN 23-Jun-29 12:46 com/intel/analytics/bigdl/friesian/feature/Utils$$anonfun$11.class
+-rw----     2.0 fat     2631 bl defN 23-Jun-29 12:46 com/intel/analytics/bigdl/friesian/feature/Utils$$anonfun$addNegativeList$1.class
+-rw----     2.0 fat     1365 bl defN 23-Jun-29 12:46 com/intel/analytics/bigdl/friesian/feature/Utils$$anonfun$10.class
+-rw----     2.0 fat     2159 bl defN 23-Jun-29 12:46 com/intel/analytics/bigdl/friesian/feature/Utils$$anonfun$addNegativeList$1$$anonfun$9$$anonfun$apply$2.class
+-rw----     2.0 fat     3166 bl defN 23-Jun-29 12:46 com/intel/analytics/bigdl/friesian/feature/Utils$$typecreator2$1.class
+-rw----     2.0 fat     1379 bl defN 23-Jun-29 12:46 com/intel/analytics/bigdl/friesian/feature/Utils$$anonfun$getClipFunc$1.class
+-rw----     2.0 fat     1374 bl defN 23-Jun-29 12:46 com/intel/analytics/bigdl/friesian/feature/Utils$$anonfun$padArr$1$$anonfun$7.class
+-rw----     2.0 fat     3238 bl defN 23-Jun-29 12:46 com/intel/analytics/bigdl/friesian/feature/Utils$$typecreator4$1.class
+-rw----     2.0 fat     1478 bl defN 23-Jun-29 12:46 com/intel/analytics/bigdl/friesian/feature/Utils$$anonfun$6$$anonfun$apply$5.class
+-rw----     2.0 fat        0 bl defN 23-Jun-29 12:46 META-INF/maven/
+-rw----     2.0 fat        0 bl defN 23-Jun-29 12:46 META-INF/maven/com.intel.analytics.bigdl/
+-rw----     2.0 fat        0 bl defN 23-Jun-29 12:46 META-INF/maven/com.intel.analytics.bigdl/bigdl-friesian-spark_2.4.6/
+-rw----     2.0 fat    28637 bl defN 23-Jun-27 15:53 META-INF/maven/com.intel.analytics.bigdl/bigdl-friesian-spark_2.4.6/pom.xml
+-rw----     2.0 fat      145 bl defN 23-Jun-29 12:43 META-INF/maven/com.intel.analytics.bigdl/bigdl-friesian-spark_2.4.6/pom.properties
+113 files, 342364 bytes uncompressed, 131021 bytes compressed:  61.7%
```

### zipnote «TEMP»/diffoscope_vi62uqag_/tmpkqww41c9_.zip

```diff
@@ -1,13 +1,16 @@
 Filename: META-INF/
 Comment: 
 
 Filename: META-INF/MANIFEST.MF
 Comment: 
 
+Filename: app.properties
+Comment: 
+
 Filename: com/
 Comment: 
 
 Filename: com/intel/
 Comment: 
 
 Filename: com/intel/analytics/
@@ -15,315 +18,312 @@
 
 Filename: com/intel/analytics/bigdl/
 Comment: 
 
 Filename: com/intel/analytics/bigdl/friesian/
 Comment: 
 
-Filename: com/intel/analytics/bigdl/friesian/feature/
-Comment: 
-
-Filename: com/intel/analytics/bigdl/friesian/feature/Utils$$anonfun$maskArr$1.class
+Filename: com/intel/analytics/bigdl/friesian/python/
 Comment: 
 
-Filename: com/intel/analytics/bigdl/friesian/feature/Utils$$typecreator3$1.class
+Filename: com/intel/analytics/bigdl/friesian/python/PythonFriesian$$anonfun$clip$2.class
 Comment: 
 
-Filename: com/intel/analytics/bigdl/friesian/feature/Utils$$anonfun$getMedian$1.class
+Filename: com/intel/analytics/bigdl/friesian/python/PythonFriesian$$anonfun$postPad$1$$typecreator15$1.class
 Comment: 
 
-Filename: com/intel/analytics/bigdl/friesian/feature/Utils$$anonfun$10.class
+Filename: com/intel/analytics/bigdl/friesian/python/PythonFriesian$$anonfun$postPad$1$$typecreator7$1.class
 Comment: 
 
-Filename: com/intel/analytics/bigdl/friesian/feature/Utils$$anonfun$12$$anonfun$apply$3.class
+Filename: com/intel/analytics/bigdl/friesian/python/PythonFriesian$$anonfun$log$2.class
 Comment: 
 
-Filename: com/intel/analytics/bigdl/friesian/feature/Utils$$anonfun$maskArr$1$$anonfun$1.class
+Filename: com/intel/analytics/bigdl/friesian/python/PythonFriesian$$anonfun$log$1.class
 Comment: 
 
-Filename: com/intel/analytics/bigdl/friesian/feature/Utils$$anonfun$addNegativeList$1.class
+Filename: com/intel/analytics/bigdl/friesian/python/PythonFriesian$$anonfun$crossColumns$1.class
 Comment: 
 
-Filename: com/intel/analytics/bigdl/friesian/feature/Utils$$anonfun$padMatrix$1$$anonfun$8.class
+Filename: com/intel/analytics/bigdl/friesian/python/PythonFriesian$$anonfun$17.class
 Comment: 
 
-Filename: com/intel/analytics/bigdl/friesian/feature/Utils$$anonfun$13$$anonfun$apply$9.class
+Filename: com/intel/analytics/bigdl/friesian/python/PythonFriesian.class
 Comment: 
 
-Filename: com/intel/analytics/bigdl/friesian/feature/Utils$$anonfun$6$$anonfun$apply$6.class
+Filename: com/intel/analytics/bigdl/friesian/python/PythonFriesian$$anonfun$postPad$1.class
 Comment: 
 
-Filename: com/intel/analytics/bigdl/friesian/feature/Utils$$anonfun$4.class
+Filename: com/intel/analytics/bigdl/friesian/python/PythonFriesian$$anonfun$postPad$1$$typecreator6$1.class
 Comment: 
 
-Filename: com/intel/analytics/bigdl/friesian/feature/Utils$$anonfun$6.class
+Filename: com/intel/analytics/bigdl/friesian/python/PythonFriesian$$anonfun$clip$1.class
 Comment: 
 
-Filename: com/intel/analytics/bigdl/friesian/feature/Utils$$anonfun$getClipFunc$3.class
+Filename: com/intel/analytics/bigdl/friesian/python/PythonFriesian$$anonfun$4.class
 Comment: 
 
-Filename: com/intel/analytics/bigdl/friesian/feature/Utils$$anonfun$addNegtiveItem$1.class
+Filename: com/intel/analytics/bigdl/friesian/python/PythonFriesian$$anonfun$mask$1.class
 Comment: 
 
-Filename: com/intel/analytics/bigdl/friesian/feature/Utils$$anonfun$maskArr$1$$anonfun$3.class
+Filename: com/intel/analytics/bigdl/friesian/python/PythonFriesian$$anonfun$22.class
 Comment: 
 
-Filename: com/intel/analytics/bigdl/friesian/feature/Utils$$anonfun$12.class
+Filename: com/intel/analytics/bigdl/friesian/python/PythonFriesian$$anonfun$postPad$1$$typecreator10$1.class
 Comment: 
 
-Filename: com/intel/analytics/bigdl/friesian/feature/Utils$$anonfun$4$$anonfun$apply$mcII$sp$1.class
+Filename: com/intel/analytics/bigdl/friesian/python/PythonFriesian$$anonfun$23.class
 Comment: 
 
-Filename: com/intel/analytics/bigdl/friesian/feature/Utils$$anonfun$padArr$1.class
+Filename: com/intel/analytics/bigdl/friesian/python/PythonFriesian$$anonfun$19.class
 Comment: 
 
-Filename: com/intel/analytics/bigdl/friesian/feature/Utils$$anonfun$getClipFunc$2.class
+Filename: com/intel/analytics/bigdl/friesian/python/PythonFriesian$$typecreator1$1.class
 Comment: 
 
-Filename: com/intel/analytics/bigdl/friesian/feature/Utils$$anonfun$padMatrix$1.class
+Filename: com/intel/analytics/bigdl/friesian/python/PythonFriesian$$anonfun$postPad$1$$typecreator4$1.class
 Comment: 
 
-Filename: com/intel/analytics/bigdl/friesian/feature/Utils$$anonfun$padMatrix$1$$anonfun$8$$anonfun$apply$7.class
+Filename: com/intel/analytics/bigdl/friesian/python/PythonFriesian$$anonfun$21$$anonfun$apply$2.class
 Comment: 
 
-Filename: com/intel/analytics/bigdl/friesian/feature/Utils$$anonfun$addNegativeList$1$$anonfun$9$$anonfun$apply$2.class
+Filename: com/intel/analytics/bigdl/friesian/python/PythonFriesian$$anonfun$postPad$1$$typecreator9$1.class
 Comment: 
 
-Filename: com/intel/analytics/bigdl/friesian/feature/Utils$.class
+Filename: com/intel/analytics/bigdl/friesian/python/PythonFriesian$$anonfun$postPad$1$$typecreator5$1.class
 Comment: 
 
-Filename: com/intel/analytics/bigdl/friesian/feature/Utils$$anonfun$maskArr$1$$anonfun$2.class
+Filename: com/intel/analytics/bigdl/friesian/python/PythonFriesian$$typecreator2$1.class
 Comment: 
 
-Filename: com/intel/analytics/bigdl/friesian/feature/Utils$$anonfun$13$$anonfun$apply$9$$anonfun$apply$4.class
+Filename: com/intel/analytics/bigdl/friesian/python/PythonFriesian$$anonfun$postPad$1$$typecreator19$1.class
 Comment: 
 
-Filename: com/intel/analytics/bigdl/friesian/feature/Utils$$anonfun$13.class
+Filename: com/intel/analytics/bigdl/friesian/python/PythonFriesian$$anonfun$9$$anonfun$12$$anonfun$13.class
 Comment: 
 
-Filename: com/intel/analytics/bigdl/friesian/feature/Utils$$anonfun$addNegativeList$1$$anonfun$9.class
+Filename: com/intel/analytics/bigdl/friesian/python/PythonFriesian$$anonfun$postPad$1$$typecreator17$1.class
 Comment: 
 
-Filename: com/intel/analytics/bigdl/friesian/feature/Utils$$anonfun$12$$anonfun$apply$3$$anonfun$apply$mcII$sp$2.class
+Filename: com/intel/analytics/bigdl/friesian/python/PythonFriesian$$anonfun$15.class
 Comment: 
 
-Filename: com/intel/analytics/bigdl/friesian/feature/Utils$$typecreator1$1.class
+Filename: com/intel/analytics/bigdl/friesian/python/PythonFriesian$$anonfun$6.class
 Comment: 
 
-Filename: com/intel/analytics/bigdl/friesian/feature/Utils$$anonfun$6$$anonfun$apply$5.class
+Filename: com/intel/analytics/bigdl/friesian/python/PythonFriesian$$anonfun$1.class
 Comment: 
 
-Filename: com/intel/analytics/bigdl/friesian/feature/Utils$$anonfun$getIndex$1.class
+Filename: com/intel/analytics/bigdl/friesian/python/PythonFriesian$$anonfun$postPad$1$$typecreator11$1.class
 Comment: 
 
-Filename: com/intel/analytics/bigdl/friesian/feature/Utils$$typecreator4$1.class
+Filename: com/intel/analytics/bigdl/friesian/python/PythonFriesian$$anonfun$8.class
 Comment: 
 
-Filename: com/intel/analytics/bigdl/friesian/feature/Utils$$anonfun$5.class
+Filename: com/intel/analytics/bigdl/friesian/python/PythonFriesian$$anonfun$postPad$1$$typecreator12$1.class
 Comment: 
 
-Filename: com/intel/analytics/bigdl/friesian/feature/Utils$$anonfun$addNegtiveItem$1$$anonfun$apply$1.class
+Filename: com/intel/analytics/bigdl/friesian/python/PythonFriesian$$anonfun$postPad$1$$typecreator16$1.class
 Comment: 
 
-Filename: com/intel/analytics/bigdl/friesian/feature/Utils$$anonfun$getClipFunc$1.class
+Filename: com/intel/analytics/bigdl/friesian/python/PythonFriesian$$anonfun$16.class
 Comment: 
 
-Filename: com/intel/analytics/bigdl/friesian/feature/Utils$$anonfun$13$$anonfun$apply$9$$anonfun$apply$4$$anonfun$apply$mcII$sp$3.class
+Filename: com/intel/analytics/bigdl/friesian/python/PythonFriesian$$anonfun$5.class
 Comment: 
 
-Filename: com/intel/analytics/bigdl/friesian/feature/Utils$$anonfun$addNegtiveItem$1$$anonfun$apply$8.class
+Filename: com/intel/analytics/bigdl/friesian/python/PythonFriesian$$typecreator3$1.class
 Comment: 
 
-Filename: com/intel/analytics/bigdl/friesian/feature/Utils$$anonfun$11.class
+Filename: com/intel/analytics/bigdl/friesian/python/PythonFriesian$$anonfun$addValueFeatures$1.class
 Comment: 
 
-Filename: com/intel/analytics/bigdl/friesian/feature/Utils.class
+Filename: com/intel/analytics/bigdl/friesian/python/PythonFriesian$$anonfun$5$$anonfun$apply$1.class
 Comment: 
 
-Filename: com/intel/analytics/bigdl/friesian/feature/Utils$$anonfun$padArr$1$$anonfun$7.class
+Filename: com/intel/analytics/bigdl/friesian/python/PythonFriesian$$anonfun$postPad$1$$typecreator14$1.class
 Comment: 
 
-Filename: com/intel/analytics/bigdl/friesian/feature/Utils$$typecreator2$1.class
+Filename: com/intel/analytics/bigdl/friesian/python/PythonFriesian$$anonfun$com$intel$analytics$bigdl$friesian$python$PythonFriesian$$crossColumns$1$1.class
 Comment: 
 
-Filename: com/intel/analytics/bigdl/friesian/python/
+Filename: com/intel/analytics/bigdl/friesian/python/PythonFriesian$.class
 Comment: 
 
-Filename: com/intel/analytics/bigdl/friesian/python/PythonFriesian$$anonfun$21$$anonfun$apply$2.class
+Filename: com/intel/analytics/bigdl/friesian/python/PythonFriesian$$anonfun$crossColumns$1$$anonfun$apply$mcVI$sp$1.class
 Comment: 
 
-Filename: com/intel/analytics/bigdl/friesian/python/PythonFriesian$$anonfun$23.class
+Filename: com/intel/analytics/bigdl/friesian/python/PythonFriesian$$anonfun$9$$anonfun$11.class
 Comment: 
 
-Filename: com/intel/analytics/bigdl/friesian/python/PythonFriesian$$anonfun$9$$anonfun$12.class
+Filename: com/intel/analytics/bigdl/friesian/python/PythonFriesian$$anonfun$9.class
 Comment: 
 
-Filename: com/intel/analytics/bigdl/friesian/python/PythonFriesian$$anonfun$clip$1.class
+Filename: com/intel/analytics/bigdl/friesian/python/PythonFriesian$$anonfun$7.class
 Comment: 
 
-Filename: com/intel/analytics/bigdl/friesian/python/PythonFriesian$$anonfun$crossColumns$1.class
+Filename: com/intel/analytics/bigdl/friesian/python/PythonFriesian$$anonfun$postPad$1$$typecreator13$1.class
 Comment: 
 
-Filename: com/intel/analytics/bigdl/friesian/python/PythonFriesian$$anonfun$addValueFeatures$1.class
+Filename: com/intel/analytics/bigdl/friesian/python/PythonFriesian$$anonfun$21.class
 Comment: 
 
-Filename: com/intel/analytics/bigdl/friesian/python/PythonFriesian$$anonfun$mask$1.class
+Filename: com/intel/analytics/bigdl/friesian/python/PythonFriesian$$anonfun$9$$anonfun$10.class
 Comment: 
 
-Filename: com/intel/analytics/bigdl/friesian/python/PythonFriesian$$anonfun$postPad$1$$typecreator13$1.class
+Filename: com/intel/analytics/bigdl/friesian/python/PythonFriesian$$anonfun$20.class
 Comment: 
 
-Filename: com/intel/analytics/bigdl/friesian/python/PythonFriesian$$anonfun$18.class
+Filename: com/intel/analytics/bigdl/friesian/python/PythonFriesian$$anonfun$postPad$1$$typecreator18$1.class
 Comment: 
 
-Filename: com/intel/analytics/bigdl/friesian/python/PythonFriesian$$anonfun$postPad$1$$typecreator19$1.class
+Filename: com/intel/analytics/bigdl/friesian/python/PythonFriesian$$anonfun$3.class
 Comment: 
 
-Filename: com/intel/analytics/bigdl/friesian/python/PythonFriesian$$anonfun$postPad$1$$typecreator11$1.class
+Filename: com/intel/analytics/bigdl/friesian/python/PythonFriesian$$anonfun$postPad$1$$typecreator8$1.class
 Comment: 
 
-Filename: com/intel/analytics/bigdl/friesian/python/PythonFriesian$$anonfun$postPad$1$$typecreator17$1.class
+Filename: com/intel/analytics/bigdl/friesian/python/PythonFriesian$$anonfun$21$$anonfun$apply$3.class
 Comment: 
 
-Filename: com/intel/analytics/bigdl/friesian/python/PythonFriesian$$anonfun$postPad$1$$typecreator9$1.class
+Filename: com/intel/analytics/bigdl/friesian/python/PythonFriesian$$anonfun$18.class
 Comment: 
 
-Filename: com/intel/analytics/bigdl/friesian/python/PythonFriesian$$anonfun$20.class
+Filename: com/intel/analytics/bigdl/friesian/python/PythonFriesian$$anonfun$14.class
 Comment: 
 
-Filename: com/intel/analytics/bigdl/friesian/python/PythonFriesian$$anonfun$postPad$1$$typecreator4$1.class
+Filename: com/intel/analytics/bigdl/friesian/python/PythonFriesian$$anonfun$9$$anonfun$12.class
 Comment: 
 
-Filename: com/intel/analytics/bigdl/friesian/python/PythonFriesian$$anonfun$log$1.class
+Filename: com/intel/analytics/bigdl/friesian/python/PythonFriesian$$anonfun$2.class
 Comment: 
 
-Filename: com/intel/analytics/bigdl/friesian/python/PythonFriesian$$anonfun$postPad$1$$typecreator8$1.class
+Filename: com/intel/analytics/bigdl/friesian/feature/
 Comment: 
 
-Filename: com/intel/analytics/bigdl/friesian/python/PythonFriesian$$anonfun$postPad$1$$typecreator16$1.class
+Filename: com/intel/analytics/bigdl/friesian/feature/Utils$$anonfun$12$$anonfun$apply$3.class
 Comment: 
 
-Filename: com/intel/analytics/bigdl/friesian/python/PythonFriesian$$anonfun$6.class
+Filename: com/intel/analytics/bigdl/friesian/feature/Utils$$anonfun$5.class
 Comment: 
 
-Filename: com/intel/analytics/bigdl/friesian/python/PythonFriesian$$anonfun$9$$anonfun$10.class
+Filename: com/intel/analytics/bigdl/friesian/feature/Utils$$anonfun$padMatrix$1.class
 Comment: 
 
-Filename: com/intel/analytics/bigdl/friesian/python/PythonFriesian$.class
+Filename: com/intel/analytics/bigdl/friesian/feature/Utils$$anonfun$13$$anonfun$apply$9.class
 Comment: 
 
-Filename: com/intel/analytics/bigdl/friesian/python/PythonFriesian.class
+Filename: com/intel/analytics/bigdl/friesian/feature/Utils$$anonfun$6.class
 Comment: 
 
-Filename: com/intel/analytics/bigdl/friesian/python/PythonFriesian$$anonfun$postPad$1$$typecreator14$1.class
+Filename: com/intel/analytics/bigdl/friesian/feature/Utils$$anonfun$addNegativeList$1$$anonfun$9.class
 Comment: 
 
-Filename: com/intel/analytics/bigdl/friesian/python/PythonFriesian$$anonfun$9.class
+Filename: com/intel/analytics/bigdl/friesian/feature/Utils$$anonfun$addNegtiveItem$1.class
 Comment: 
 
-Filename: com/intel/analytics/bigdl/friesian/python/PythonFriesian$$anonfun$22.class
+Filename: com/intel/analytics/bigdl/friesian/feature/Utils$$anonfun$getClipFunc$3.class
 Comment: 
 
-Filename: com/intel/analytics/bigdl/friesian/python/PythonFriesian$$anonfun$postPad$1$$typecreator7$1.class
+Filename: com/intel/analytics/bigdl/friesian/feature/Utils.class
 Comment: 
 
-Filename: com/intel/analytics/bigdl/friesian/python/PythonFriesian$$anonfun$1.class
+Filename: com/intel/analytics/bigdl/friesian/feature/Utils$$anonfun$getClipFunc$2.class
 Comment: 
 
-Filename: com/intel/analytics/bigdl/friesian/python/PythonFriesian$$anonfun$crossColumns$1$$anonfun$apply$mcVI$sp$1.class
+Filename: com/intel/analytics/bigdl/friesian/feature/Utils$$typecreator3$1.class
 Comment: 
 
-Filename: com/intel/analytics/bigdl/friesian/python/PythonFriesian$$typecreator1$1.class
+Filename: com/intel/analytics/bigdl/friesian/feature/Utils$$anonfun$4$$anonfun$apply$mcII$sp$1.class
 Comment: 
 
-Filename: com/intel/analytics/bigdl/friesian/python/PythonFriesian$$anonfun$postPad$1$$typecreator18$1.class
+Filename: com/intel/analytics/bigdl/friesian/feature/Utils$$anonfun$6$$anonfun$apply$6.class
 Comment: 
 
-Filename: com/intel/analytics/bigdl/friesian/python/PythonFriesian$$typecreator2$1.class
+Filename: com/intel/analytics/bigdl/friesian/feature/Utils$$anonfun$addNegtiveItem$1$$anonfun$apply$1.class
 Comment: 
 
-Filename: com/intel/analytics/bigdl/friesian/python/PythonFriesian$$anonfun$9$$anonfun$12$$anonfun$13.class
+Filename: com/intel/analytics/bigdl/friesian/feature/Utils$$anonfun$maskArr$1$$anonfun$2.class
 Comment: 
 
-Filename: com/intel/analytics/bigdl/friesian/python/PythonFriesian$$anonfun$17.class
+Filename: com/intel/analytics/bigdl/friesian/feature/Utils$$anonfun$getIndex$1.class
 Comment: 
 
-Filename: com/intel/analytics/bigdl/friesian/python/PythonFriesian$$anonfun$postPad$1.class
+Filename: com/intel/analytics/bigdl/friesian/feature/Utils$$anonfun$getMedian$1.class
 Comment: 
 
-Filename: com/intel/analytics/bigdl/friesian/python/PythonFriesian$$anonfun$9$$anonfun$11.class
+Filename: com/intel/analytics/bigdl/friesian/feature/Utils$$anonfun$12$$anonfun$apply$3$$anonfun$apply$mcII$sp$2.class
 Comment: 
 
-Filename: com/intel/analytics/bigdl/friesian/python/PythonFriesian$$anonfun$log$2.class
+Filename: com/intel/analytics/bigdl/friesian/feature/Utils$$anonfun$maskArr$1.class
 Comment: 
 
-Filename: com/intel/analytics/bigdl/friesian/python/PythonFriesian$$anonfun$clip$2.class
+Filename: com/intel/analytics/bigdl/friesian/feature/Utils$$anonfun$13.class
 Comment: 
 
-Filename: com/intel/analytics/bigdl/friesian/python/PythonFriesian$$anonfun$14.class
+Filename: com/intel/analytics/bigdl/friesian/feature/Utils$$anonfun$maskArr$1$$anonfun$3.class
 Comment: 
 
-Filename: com/intel/analytics/bigdl/friesian/python/PythonFriesian$$anonfun$postPad$1$$typecreator15$1.class
+Filename: com/intel/analytics/bigdl/friesian/feature/Utils$$anonfun$maskArr$1$$anonfun$1.class
 Comment: 
 
-Filename: com/intel/analytics/bigdl/friesian/python/PythonFriesian$$anonfun$5.class
+Filename: com/intel/analytics/bigdl/friesian/feature/Utils$$anonfun$4.class
 Comment: 
 
-Filename: com/intel/analytics/bigdl/friesian/python/PythonFriesian$$anonfun$19.class
+Filename: com/intel/analytics/bigdl/friesian/feature/Utils$$anonfun$12.class
 Comment: 
 
-Filename: com/intel/analytics/bigdl/friesian/python/PythonFriesian$$anonfun$4.class
+Filename: com/intel/analytics/bigdl/friesian/feature/Utils$$anonfun$padMatrix$1$$anonfun$8$$anonfun$apply$7.class
 Comment: 
 
-Filename: com/intel/analytics/bigdl/friesian/python/PythonFriesian$$anonfun$15.class
+Filename: com/intel/analytics/bigdl/friesian/feature/Utils$$anonfun$13$$anonfun$apply$9$$anonfun$apply$4$$anonfun$apply$mcII$sp$3.class
 Comment: 
 
-Filename: com/intel/analytics/bigdl/friesian/python/PythonFriesian$$anonfun$postPad$1$$typecreator10$1.class
+Filename: com/intel/analytics/bigdl/friesian/feature/Utils$$typecreator1$1.class
 Comment: 
 
-Filename: com/intel/analytics/bigdl/friesian/python/PythonFriesian$$anonfun$8.class
+Filename: com/intel/analytics/bigdl/friesian/feature/Utils$$anonfun$padMatrix$1$$anonfun$8.class
 Comment: 
 
-Filename: com/intel/analytics/bigdl/friesian/python/PythonFriesian$$typecreator3$1.class
+Filename: com/intel/analytics/bigdl/friesian/feature/Utils$.class
 Comment: 
 
-Filename: com/intel/analytics/bigdl/friesian/python/PythonFriesian$$anonfun$postPad$1$$typecreator5$1.class
+Filename: com/intel/analytics/bigdl/friesian/feature/Utils$$anonfun$13$$anonfun$apply$9$$anonfun$apply$4.class
 Comment: 
 
-Filename: com/intel/analytics/bigdl/friesian/python/PythonFriesian$$anonfun$3.class
+Filename: com/intel/analytics/bigdl/friesian/feature/Utils$$anonfun$addNegtiveItem$1$$anonfun$apply$8.class
 Comment: 
 
-Filename: com/intel/analytics/bigdl/friesian/python/PythonFriesian$$anonfun$2.class
+Filename: com/intel/analytics/bigdl/friesian/feature/Utils$$anonfun$padArr$1.class
 Comment: 
 
-Filename: com/intel/analytics/bigdl/friesian/python/PythonFriesian$$anonfun$com$intel$analytics$bigdl$friesian$python$PythonFriesian$$crossColumns$1$1.class
+Filename: com/intel/analytics/bigdl/friesian/feature/Utils$$anonfun$11.class
 Comment: 
 
-Filename: com/intel/analytics/bigdl/friesian/python/PythonFriesian$$anonfun$21.class
+Filename: com/intel/analytics/bigdl/friesian/feature/Utils$$anonfun$addNegativeList$1.class
 Comment: 
 
-Filename: com/intel/analytics/bigdl/friesian/python/PythonFriesian$$anonfun$5$$anonfun$apply$1.class
+Filename: com/intel/analytics/bigdl/friesian/feature/Utils$$anonfun$10.class
 Comment: 
 
-Filename: com/intel/analytics/bigdl/friesian/python/PythonFriesian$$anonfun$16.class
+Filename: com/intel/analytics/bigdl/friesian/feature/Utils$$anonfun$addNegativeList$1$$anonfun$9$$anonfun$apply$2.class
 Comment: 
 
-Filename: com/intel/analytics/bigdl/friesian/python/PythonFriesian$$anonfun$postPad$1$$typecreator6$1.class
+Filename: com/intel/analytics/bigdl/friesian/feature/Utils$$typecreator2$1.class
 Comment: 
 
-Filename: com/intel/analytics/bigdl/friesian/python/PythonFriesian$$anonfun$21$$anonfun$apply$3.class
+Filename: com/intel/analytics/bigdl/friesian/feature/Utils$$anonfun$getClipFunc$1.class
 Comment: 
 
-Filename: com/intel/analytics/bigdl/friesian/python/PythonFriesian$$anonfun$7.class
+Filename: com/intel/analytics/bigdl/friesian/feature/Utils$$anonfun$padArr$1$$anonfun$7.class
 Comment: 
 
-Filename: com/intel/analytics/bigdl/friesian/python/PythonFriesian$$anonfun$postPad$1$$typecreator12$1.class
+Filename: com/intel/analytics/bigdl/friesian/feature/Utils$$typecreator4$1.class
 Comment: 
 
-Filename: app.properties
+Filename: com/intel/analytics/bigdl/friesian/feature/Utils$$anonfun$6$$anonfun$apply$5.class
 Comment: 
 
 Filename: META-INF/maven/
 Comment: 
 
 Filename: META-INF/maven/com.intel.analytics.bigdl/
 Comment:
```

### META-INF/MANIFEST.MF

```diff
@@ -1,6 +1,6 @@
 Manifest-Version: 1.0
 Archiver-Version: Plexus Archiver
 Built-By: root
 Created-By: Apache Maven 3.8.2
-Build-Jdk: 1.8.0_372
+Build-Jdk: 1.8.0_345
```

### com/intel/analytics/bigdl/friesian/feature/Utils$$anonfun$addNegativeList$1.class

#### procyon -ec {}

```diff
@@ -1,24 +1,24 @@
 
 package com.intel.analytics.bigdl.friesian.feature;
 
 import scala.Function1;
 import scala.collection.immutable.IndexedSeq$;
 import scala.Predef$;
 import scala.runtime.RichInt$;
-import scala.util.Random;
+import java.security.SecureRandom;
 import scala.Serializable;
 import scala.collection.Seq;
 import scala.collection.mutable.WrappedArray;
 import scala.runtime.AbstractFunction1;
 
 public final class Utils$$anonfun$addNegativeList$1 extends AbstractFunction1<WrappedArray<Object>, Seq<Seq<Object>>> implements Serializable {
     public static final long serialVersionUID = 0L;
     public final int negNum$2;
     public final int itemSize$2;
     
     public final Seq<Seq<Object>> apply(final WrappedArray<Object> history) {
-        final Random r = new Random();
+        final SecureRandom r = new SecureRandom();
         final Seq negItemSeq = (Seq)RichInt$.MODULE$.to$extension0(Predef$.MODULE$.intWrapper(0), history.length() - 1).map((Function1)new Utils$$anonfun$addNegativeList$1$$anonfun.Utils$$anonfun$addNegativeList$1$$anonfun$9(this, r, (WrappedArray)history), IndexedSeq$.MODULE$.canBuildFrom());
         return (Seq<Seq<Object>>)negItemSeq;
     }
 }
```

### com/intel/analytics/bigdl/friesian/feature/Utils$$anonfun$addNegtiveItem$1.class

#### procyon -ec {}

```diff
@@ -6,23 +6,23 @@
 import scala.Tuple2$mcII$sp;
 import scala.collection.Seq$;
 import scala.Function1;
 import scala.collection.immutable.IndexedSeq$;
 import scala.Predef$;
 import scala.runtime.RichInt$;
 import scala.collection.TraversableLike;
-import scala.util.Random;
+import java.security.SecureRandom;
 import scala.Serializable;
 import scala.Tuple2;
 import scala.collection.Seq;
 import scala.runtime.AbstractFunction1;
 
 public final class Utils$$anonfun$addNegtiveItem$1 extends AbstractFunction1<Object, Seq<Tuple2<Object, Object>>> implements Serializable {
     public static final long serialVersionUID = 0L;
     private final int negNum$1;
     public final int itemSize$1;
-    public final Random r$1;
+    public final SecureRandom r$1;
     
     public final Seq<Tuple2<Object, Object>> apply(final int itemId) {
         return (Seq<Tuple2<Object, Object>>)((TraversableLike)((TraversableLike)RichInt$.MODULE$.to$extension0(Predef$.MODULE$.intWrapper(1), this.negNum$1).map((Function1)new Utils$$anonfun$addNegtiveItem$1$$anonfun$apply.Utils$$anonfun$addNegtiveItem$1$$anonfun$apply$1(this, itemId), IndexedSeq$.MODULE$.canBuildFrom())).map((Function1)new Utils$$anonfun$addNegtiveItem$1$$anonfun$apply.Utils$$anonfun$addNegtiveItem$1$$anonfun$apply$8(this), IndexedSeq$.MODULE$.canBuildFrom())).$plus$plus((GenTraversableOnce)Seq$.MODULE$.apply((Seq)Predef$.MODULE$.wrapRefArray((Object[])new Tuple2[] { (Tuple2)new Tuple2$mcII$sp(itemId, 1) })), IndexedSeq$.MODULE$.canBuildFrom());
     }
 }
```

### com/intel/analytics/bigdl/friesian/feature/Utils$$anonfun$addNegativeList$1$$anonfun$9$$anonfun$apply$2.class

#### javap -verbose -constants -s -l -private {}

```diff
@@ -1,8 +1,8 @@
-  SHA-256 checksum fee959618145d4da43a7fb13e4a3cf975331ae69b9cd2606db9d2ac485d7967a
+  SHA-256 checksum 1547d3d44a34f723077a0f5de4c7b7508551bde68b7de298123d207c4c59ebd8
   Compiled from "Utils.scala"
 public final class com.intel.analytics.bigdl.friesian.feature.Utils$$anonfun$addNegativeList$1$$anonfun$9$$anonfun$apply$2 extends scala.runtime.AbstractFunction1$mcII$sp implements scala.Serializable
   minor version: 0
   major version: 50
   flags: (0x0031) ACC_PUBLIC, ACC_FINAL, ACC_SUPER
   this_class: #2                          // com/intel/analytics/bigdl/friesian/feature/Utils$$anonfun$addNegativeList$1$$anonfun$9$$anonfun$apply$2
   super_class: #4                         // scala/runtime/AbstractFunction1$mcII$sp
@@ -33,29 +33,29 @@
   #24 = Methodref          #2.#23         // com/intel/analytics/bigdl/friesian/feature/Utils$$anonfun$addNegativeList$1$$anonfun$9$$anonfun$apply$2.apply$mcII$sp:(I)I
   #25 = Utf8               this
   #26 = Utf8               Lcom/intel/analytics/bigdl/friesian/feature/Utils$$anonfun$addNegativeList$1$$anonfun$9$$anonfun$apply$2;
   #27 = Utf8               j
   #28 = NameAndType        #16:#17        // $outer:Lcom/intel/analytics/bigdl/friesian/feature/Utils$$anonfun$addNegativeList$1$$anonfun$9;
   #29 = Fieldref           #2.#28         // com/intel/analytics/bigdl/friesian/feature/Utils$$anonfun$addNegativeList$1$$anonfun$9$$anonfun$apply$2.$outer:Lcom/intel/analytics/bigdl/friesian/feature/Utils$$anonfun$addNegativeList$1$$anonfun$9;
   #30 = Utf8               r$2
-  #31 = Utf8               Lscala/util/Random;
-  #32 = NameAndType        #30:#31        // r$2:Lscala/util/Random;
-  #33 = Fieldref           #9.#32         // com/intel/analytics/bigdl/friesian/feature/Utils$$anonfun$addNegativeList$1$$anonfun$9.r$2:Lscala/util/Random;
+  #31 = Utf8               Ljava/security/SecureRandom;
+  #32 = NameAndType        #30:#31        // r$2:Ljava/security/SecureRandom;
+  #33 = Fieldref           #9.#32         // com/intel/analytics/bigdl/friesian/feature/Utils$$anonfun$addNegativeList$1$$anonfun$9.r$2:Ljava/security/SecureRandom;
   #34 = Utf8               com$intel$analytics$bigdl$friesian$feature$Utils$$anonfun$$anonfun$$$outer
   #35 = Utf8               ()Lcom/intel/analytics/bigdl/friesian/feature/Utils$$anonfun$addNegativeList$1;
   #36 = NameAndType        #34:#35        // com$intel$analytics$bigdl$friesian$feature$Utils$$anonfun$$anonfun$$$outer:()Lcom/intel/analytics/bigdl/friesian/feature/Utils$$anonfun$addNegativeList$1;
   #37 = Methodref          #9.#36         // com/intel/analytics/bigdl/friesian/feature/Utils$$anonfun$addNegativeList$1$$anonfun$9.com$intel$analytics$bigdl$friesian$feature$Utils$$anonfun$$anonfun$$$outer:()Lcom/intel/analytics/bigdl/friesian/feature/Utils$$anonfun$addNegativeList$1;
   #38 = Utf8               itemSize$2
   #39 = NameAndType        #38:#19        // itemSize$2:I
   #40 = Fieldref           #11.#39        // com/intel/analytics/bigdl/friesian/feature/Utils$$anonfun$addNegativeList$1.itemSize$2:I
-  #41 = Utf8               scala/util/Random
-  #42 = Class              #41            // scala/util/Random
+  #41 = Utf8               java/security/SecureRandom
+  #42 = Class              #41            // java/security/SecureRandom
   #43 = Utf8               nextInt
   #44 = NameAndType        #43:#21        // nextInt:(I)I
-  #45 = Methodref          #42.#44        // scala/util/Random.nextInt:(I)I
+  #45 = Methodref          #42.#44        // java/security/SecureRandom.nextInt:(I)I
   #46 = Utf8               history$1
   #47 = Utf8               Lscala/collection/mutable/WrappedArray;
   #48 = NameAndType        #46:#47        // history$1:Lscala/collection/mutable/WrappedArray;
   #49 = Fieldref           #9.#48         // com/intel/analytics/bigdl/friesian/feature/Utils$$anonfun$addNegativeList$1$$anonfun$9.history$1:Lscala/collection/mutable/WrappedArray;
   #50 = NameAndType        #18:#19        // i$1:I
   #51 = Fieldref           #2.#50         // com/intel/analytics/bigdl/friesian/feature/Utils$$anonfun$addNegativeList$1$$anonfun$9$$anonfun$apply$2.i$1:I
   #52 = Utf8               scala/collection/mutable/WrappedArray
@@ -130,22 +130,22 @@
     Code:
       stack=4, locals=3, args_size=2
          0: iconst_0
          1: istore_2
          2: iconst_1
          3: aload_0
          4: getfield      #29                 // Field $outer:Lcom/intel/analytics/bigdl/friesian/feature/Utils$$anonfun$addNegativeList$1$$anonfun$9;
-         7: getfield      #33                 // Field com/intel/analytics/bigdl/friesian/feature/Utils$$anonfun$addNegativeList$1$$anonfun$9.r$2:Lscala/util/Random;
+         7: getfield      #33                 // Field com/intel/analytics/bigdl/friesian/feature/Utils$$anonfun$addNegativeList$1$$anonfun$9.r$2:Ljava/security/SecureRandom;
         10: aload_0
         11: getfield      #29                 // Field $outer:Lcom/intel/analytics/bigdl/friesian/feature/Utils$$anonfun$addNegativeList$1$$anonfun$9;
         14: invokevirtual #37                 // Method com/intel/analytics/bigdl/friesian/feature/Utils$$anonfun$addNegativeList$1$$anonfun$9.com$intel$analytics$bigdl$friesian$feature$Utils$$anonfun$$anonfun$$$outer:()Lcom/intel/analytics/bigdl/friesian/feature/Utils$$anonfun$addNegativeList$1;
         17: getfield      #40                 // Field com/intel/analytics/bigdl/friesian/feature/Utils$$anonfun$addNegativeList$1.itemSize$2:I
         20: iconst_1
         21: isub
-        22: invokevirtual #45                 // Method scala/util/Random.nextInt:(I)I
+        22: invokevirtual #45                 // Method java/security/SecureRandom.nextInt:(I)I
         25: iadd
         26: istore_2
         27: iload_2
         28: aload_0
         29: getfield      #29                 // Field $outer:Lcom/intel/analytics/bigdl/friesian/feature/Utils$$anonfun$addNegativeList$1$$anonfun$9;
         32: getfield      #49                 // Field com/intel/analytics/bigdl/friesian/feature/Utils$$anonfun$addNegativeList$1$$anonfun$9.history$1:Lscala/collection/mutable/WrappedArray;
         35: aload_0
```

### com/intel/analytics/bigdl/friesian/feature/Utils$.class

#### procyon -ec {}

```diff
@@ -2,15 +2,15 @@
 package com.intel.analytics.bigdl.friesian.feature;
 
 import scala.collection.immutable.Map;
 import org.apache.spark.broadcast.Broadcast;
 import scala.collection.Seq$;
 import scala.Predef;
 import scala.collection.mutable.ArraySeq;
-import scala.util.Random;
+import java.security.SecureRandom;
 import scala.MatchError;
 import scala.Function3;
 import scala.collection.mutable.WrappedArray;
 import scala.Function2;
 import scala.Tuple2$mcII$sp;
 import org.apache.spark.TaskContext$;
 import scala.collection.immutable.Nil$;
@@ -296,20 +296,20 @@
         }
         final Object string = value.toString();
         final Object out = string;
         return (T)out;
     }
     
     public <T> Function1<Object, Seq<Tuple2<Object, Object>>> addNegtiveItem(final int negNum, final int itemSize) {
-        final Random r = new Random();
+        final SecureRandom r = new SecureRandom();
         return (Function1<Object, Seq<Tuple2<Object, Object>>>)new Utils$$anonfun$addNegtiveItem.Utils$$anonfun$addNegtiveItem$1(negNum, itemSize, r);
     }
     
     public <T> Function1<WrappedArray<Object>, Seq<Seq<Object>>> addNegativeList(final int negNum, final int itemSize) {
-        final Random r = new Random();
+        final SecureRandom r = new SecureRandom();
         return (Function1<WrappedArray<Object>, Seq<Seq<Object>>>)new Utils$$anonfun$addNegativeList.Utils$$anonfun$addNegativeList$1(negNum, itemSize);
     }
     
     public <T> Seq<Object> get1row(final Row[] full_rows, final String colName, final int index, final int lowerBound) {
         final Object colValue = full_rows[index].getAs(colName);
         final ArraySeq historySeq = (ArraySeq)Predef$.MODULE$.refArrayOps((Object[])Predef$.MODULE$.refArrayOps((Object[])full_rows).slice(lowerBound, index)).map((Function1)new Utils$$anonfun.Utils$$anonfun$10(colName), Array$.MODULE$.fallbackCanBuildFrom(Predef.Predef$DummyImplicit$.MODULE$.dummyImplicit()));
         return (Seq<Object>)Seq$.MODULE$.apply((Seq)Predef$.MODULE$.genericWrapArray((Object)new Object[] { colValue, historySeq }));
```

### com/intel/analytics/bigdl/friesian/feature/Utils$$anonfun$addNegativeList$1$$anonfun$9.class

#### procyon -ec {}

```diff
@@ -3,21 +3,21 @@
 
 import scala.runtime.BoxesRunTime;
 import scala.Function1;
 import scala.collection.immutable.IndexedSeq$;
 import scala.Predef$;
 import scala.runtime.RichInt$;
 import scala.collection.mutable.WrappedArray;
-import scala.util.Random;
+import java.security.SecureRandom;
 import scala.Serializable;
 import scala.collection.immutable.IndexedSeq;
 import scala.runtime.AbstractFunction1;
 
 public final class Utils$$anonfun$addNegativeList$1$$anonfun$9 extends AbstractFunction1<Object, IndexedSeq<Object>> implements Serializable {
     public static final long serialVersionUID = 0L;
-    public final Random r$2;
+    public final SecureRandom r$2;
     public final WrappedArray history$1;
     
     public final IndexedSeq<Object> apply(final int i) {
         return (IndexedSeq<Object>)RichInt$.MODULE$.to$extension0(Predef$.MODULE$.intWrapper(0), this.$outer.negNum$2 - 1).map((Function1)new Utils$$anonfun$addNegativeList$1$$anonfun$9$$anonfun$apply.Utils$$anonfun$addNegativeList$1$$anonfun$9$$anonfun$apply$2(this, i), IndexedSeq$.MODULE$.canBuildFrom());
     }
 }
```

### com/intel/analytics/bigdl/friesian/feature/Utils$$anonfun$addNegtiveItem$1$$anonfun$apply$1.class

#### javap -verbose -constants -s -l -private {}

```diff
@@ -1,8 +1,8 @@
-  SHA-256 checksum fa59d13d17be6f1690b797d1269a692ec5c9e3d8a96061eb1e99f2c03cfc8464
+  SHA-256 checksum a3bfea436ade7f18258e488bbd52caa694c6c8a2e0b02c338c2a1e7e9bfc6073
   Compiled from "Utils.scala"
 public final class com.intel.analytics.bigdl.friesian.feature.Utils$$anonfun$addNegtiveItem$1$$anonfun$apply$1 extends scala.runtime.AbstractFunction1$mcII$sp implements scala.Serializable
   minor version: 0
   major version: 50
   flags: (0x0031) ACC_PUBLIC, ACC_FINAL, ACC_SUPER
   this_class: #2                          // com/intel/analytics/bigdl/friesian/feature/Utils$$anonfun$addNegtiveItem$1$$anonfun$apply$1
   super_class: #4                         // scala/runtime/AbstractFunction1$mcII$sp
@@ -31,25 +31,25 @@
   #22 = Methodref          #2.#21         // com/intel/analytics/bigdl/friesian/feature/Utils$$anonfun$addNegtiveItem$1$$anonfun$apply$1.apply$mcII$sp:(I)I
   #23 = Utf8               this
   #24 = Utf8               Lcom/intel/analytics/bigdl/friesian/feature/Utils$$anonfun$addNegtiveItem$1$$anonfun$apply$1;
   #25 = Utf8               x
   #26 = NameAndType        #14:#15        // $outer:Lcom/intel/analytics/bigdl/friesian/feature/Utils$$anonfun$addNegtiveItem$1;
   #27 = Fieldref           #2.#26         // com/intel/analytics/bigdl/friesian/feature/Utils$$anonfun$addNegtiveItem$1$$anonfun$apply$1.$outer:Lcom/intel/analytics/bigdl/friesian/feature/Utils$$anonfun$addNegtiveItem$1;
   #28 = Utf8               r$1
-  #29 = Utf8               Lscala/util/Random;
-  #30 = NameAndType        #28:#29        // r$1:Lscala/util/Random;
-  #31 = Fieldref           #9.#30         // com/intel/analytics/bigdl/friesian/feature/Utils$$anonfun$addNegtiveItem$1.r$1:Lscala/util/Random;
+  #29 = Utf8               Ljava/security/SecureRandom;
+  #30 = NameAndType        #28:#29        // r$1:Ljava/security/SecureRandom;
+  #31 = Fieldref           #9.#30         // com/intel/analytics/bigdl/friesian/feature/Utils$$anonfun$addNegtiveItem$1.r$1:Ljava/security/SecureRandom;
   #32 = Utf8               itemSize$1
   #33 = NameAndType        #32:#17        // itemSize$1:I
   #34 = Fieldref           #9.#33         // com/intel/analytics/bigdl/friesian/feature/Utils$$anonfun$addNegtiveItem$1.itemSize$1:I
-  #35 = Utf8               scala/util/Random
-  #36 = Class              #35            // scala/util/Random
+  #35 = Utf8               java/security/SecureRandom
+  #36 = Class              #35            // java/security/SecureRandom
   #37 = Utf8               nextInt
   #38 = NameAndType        #37:#19        // nextInt:(I)I
-  #39 = Methodref          #36.#38        // scala/util/Random.nextInt:(I)I
+  #39 = Methodref          #36.#38        // java/security/SecureRandom.nextInt:(I)I
   #40 = NameAndType        #16:#17        // itemId$1:I
   #41 = Fieldref           #2.#40         // com/intel/analytics/bigdl/friesian/feature/Utils$$anonfun$addNegtiveItem$1$$anonfun$apply$1.itemId$1:I
   #42 = Utf8               negItem
   #43 = Utf8               (Ljava/lang/Object;)Ljava/lang/Object;
   #44 = Utf8               scala/runtime/BoxesRunTime
   #45 = Class              #44            // scala/runtime/BoxesRunTime
   #46 = Utf8               unboxToInt
@@ -115,21 +115,21 @@
     Code:
       stack=4, locals=3, args_size=2
          0: iconst_0
          1: istore_2
          2: iconst_1
          3: aload_0
          4: getfield      #27                 // Field $outer:Lcom/intel/analytics/bigdl/friesian/feature/Utils$$anonfun$addNegtiveItem$1;
-         7: getfield      #31                 // Field com/intel/analytics/bigdl/friesian/feature/Utils$$anonfun$addNegtiveItem$1.r$1:Lscala/util/Random;
+         7: getfield      #31                 // Field com/intel/analytics/bigdl/friesian/feature/Utils$$anonfun$addNegtiveItem$1.r$1:Ljava/security/SecureRandom;
         10: aload_0
         11: getfield      #27                 // Field $outer:Lcom/intel/analytics/bigdl/friesian/feature/Utils$$anonfun$addNegtiveItem$1;
         14: getfield      #34                 // Field com/intel/analytics/bigdl/friesian/feature/Utils$$anonfun$addNegtiveItem$1.itemSize$1:I
         17: iconst_1
         18: isub
-        19: invokevirtual #39                 // Method scala/util/Random.nextInt:(I)I
+        19: invokevirtual #39                 // Method java/security/SecureRandom.nextInt:(I)I
         22: iadd
         23: istore_2
         24: iload_2
         25: aload_0
         26: getfield      #41                 // Field itemId$1:I
         29: if_icmpeq     2
         32: iload_2
```

### app.properties

```diff
@@ -1,38 +1,38 @@
 #Properties
-#Mon Jun 26 04:54:09 PDT 2023
+#Thu Jun 29 12:46:03 GMT 2023
 tagsToExclude=com.intel.analytics.bigdl.tags.Integration
 orca.scope=provided
 parquet.version=1.12.2
 commons-cli.version=1.2
 jetty.jspapi.version=6.1.14
 checkstyle.version=6.6
 commons-codec.version=1.9
 make-maven-plugin.version=1.0-beta-1
 grpc.version=1.48.1
-test.build.dir=/root/actions-runner-Bree/_work/BigDL/BigDL/scala/friesian/target/test-dir
+test.build.dir=/home/runner/_work/BigDL/BigDL/scala/friesian/target/test-dir
 build-helper-maven-plugin.version=1.9
 project.build.sourceEncoding=UTF-8
 maven-checkstyle-plugin.version=2.15
 bigdl.basedir=${project.parent.basedir}
 javac.version=1.8
 serving.scope=provided
 maven-deploy-plugin.version=2.8.1
 thrift.version=0.9.2
 maven-javadoc-plugin.version=2.10.1
 maven-install-plugin.version=2.5.1
-java.version=1.8.0_372
+java.version=1.8.0_345
 commons-math.version=2.2
 wagon-ssh.version=1.0
 xerces.jdiff.version=2.11.0
 exec-maven-plugin.version=1.3.1
 findbugs.version=3.0.0
 spark-version.project=2.0
 commons-lang.version=2.6
-test.build.data=/root/actions-runner-Bree/_work/BigDL/BigDL/scala/friesian/target/test-dir
+test.build.data=/home/runner/_work/BigDL/BigDL/scala/friesian/target/test-dir
 maven-project-info-reports-plugin.version=2.7
 maven-failsafe-plugin.version=2.20.1
 maven.test.redirectTestOutputToFile=true
 maven-surefire-report-plugin.version=2.20.1
 collections.version=3.2.1
 junit5-maven-failsafe-plugin.version=2.22.2
 maven-war-plugin.version=2.4
```

### META-INF/maven/com.intel.analytics.bigdl/bigdl-friesian-spark_2.4.6/pom.properties

```diff
@@ -1,5 +1,5 @@
 #Generated by Maven
-#Mon Jun 26 04:51:18 PDT 2023
+#Thu Jun 29 12:43:04 GMT 2023
 version=2.4.0-SNAPSHOT
 groupId=com.intel.analytics.bigdl
 artifactId=bigdl-friesian-spark_2.4.6
```

## Comparing `bigdl_friesian-2.4.0b20230626.dist-info/METADATA` & `bigdl_friesian-2.4.0b20230629.dist-info/METADATA`

 * *Files 12% similar despite different names*

```diff
@@ -1,24 +1,24 @@
 Metadata-Version: 2.1
 Name: bigdl-friesian
-Version: 2.4.0b20230626
+Version: 2.4.0b20230629
 Summary: Large-scale End-to-End Recommendation Solution on Big Data
 Home-page: https://github.com/intel-analytics/BigDL
 Author: BigDL Authors
 Author-email: bigdl-user-group@googlegroups.com
 License: Apache License, Version 2.0
 Platform: mac
 Platform: linux
 Classifier: License :: OSI Approved :: Apache Software License
 Classifier: Programming Language :: Python :: 3
 Classifier: Programming Language :: Python :: 3.6
 Classifier: Programming Language :: Python :: 3.7
 Classifier: Programming Language :: Python :: Implementation :: CPython
 Description-Content-Type: text/markdown
-Requires-Dist: bigdl-orca (==2.4.0b20230626)
+Requires-Dist: bigdl-orca (==2.4.0b20230629)
 Provides-Extra: train
 Requires-Dist: bigdl-orca[ray] ; extra == 'train'
 
 
 BigDL Friesian is an application framework for building optimized 
 large-scale recommender solutions.
```

## Comparing `bigdl_friesian-2.4.0b20230626.dist-info/RECORD` & `bigdl_friesian-2.4.0b20230629.dist-info/RECORD`

 * *Files 19% similar despite different names*

```diff
@@ -1,13 +1,13 @@
 bigdl/__init__.py,sha256=FQ_uZZHR5KjpoDxPeG_JIn7bVPVa3bwrG4m33bfyYEs,940
 bigdl/friesian/__init__.py,sha256=HDuvGvKIDHxqb0oK_R440ciTIDFSQM39VbibqaMB_bA,927
 bigdl/friesian/feature/__init__.py,sha256=Ju8-zVC2fBFMHWG77uF_TTusvjoOUw3OqHGWj0TS7ao,644
 bigdl/friesian/feature/table.py,sha256=unv1LEa84_jcz6gEYRuWQLGmRdlWjIZKbZ0p-09jvck,122597
 bigdl/friesian/feature/utils.py,sha256=9vV6QQ42Xmt243YRTOHI0HCtj5EYlP40Ut5VM14Ipg0,11337
 bigdl/friesian/models/__init__.py,sha256=hvyZKXFB0pKbSpxs1h9HkW2rbI5BjfVuPAet1JZLHpA,621
 bigdl/friesian/models/tfrs_model.py,sha256=Jyj0b1x9h2Vo9JsfOwwoAAxegOu2a_RQWWTDATAQXTs,4310
-bigdl/share/friesian/lib/bigdl-friesian-spark_2.4.6-2.4.0-SNAPSHOT-jar-with-dependencies.jar,sha256=vKpPiSu0DfijDdDBcGl1tN4rr7rYBxern_GEAQHrBEc,158671
-bigdl_friesian-2.4.0b20230626.dist-info/METADATA,sha256=VufbgbW967e9TBQ7eoMRv6UcC-6Mi24cOrXVCsmbTGc,973
-bigdl_friesian-2.4.0b20230626.dist-info/WHEEL,sha256=hhtQ6nsHFIbL-_mv2i7MX9BvBTMvAXjiOmCom-m3sec,106
-bigdl_friesian-2.4.0b20230626.dist-info/dependency_links.txt,sha256=BBUQ-7v16hCAg5ZlG-k2qM9_vF8wde1CDDs0EvQrCwU,68
-bigdl_friesian-2.4.0b20230626.dist-info/top_level.txt,sha256=cBagmJYb6wgwvnIPkoHIjt6ZCR0nXudViJidCXcTXnQ,7
-bigdl_friesian-2.4.0b20230626.dist-info/RECORD,,
+bigdl/share/friesian/lib/bigdl-friesian-spark_2.4.6-2.4.0-SNAPSHOT-jar-with-dependencies.jar,sha256=8oBGt2NQwVkshVOH8d-Qff-W7aM4Quv-FJtp6cX9Jv8,158705
+bigdl_friesian-2.4.0b20230629.dist-info/METADATA,sha256=Bbn81Ehg7SfqGAi6hS5qDs_fQmbiJKlvMpcG2DWYt5g,973
+bigdl_friesian-2.4.0b20230629.dist-info/WHEEL,sha256=-kQi_VMfvRQozZJT7HUPMfY-5vLo0LVTmAylNJ3Ft98,106
+bigdl_friesian-2.4.0b20230629.dist-info/dependency_links.txt,sha256=BBUQ-7v16hCAg5ZlG-k2qM9_vF8wde1CDDs0EvQrCwU,68
+bigdl_friesian-2.4.0b20230629.dist-info/top_level.txt,sha256=cBagmJYb6wgwvnIPkoHIjt6ZCR0nXudViJidCXcTXnQ,7
+bigdl_friesian-2.4.0b20230629.dist-info/RECORD,,
```

